lib_ml_remla/__init__.py
lib_ml_remla/preprocess.py
lib_ml_remla/utils.py
lib_ml_remla10_2024-1.0.2.dist-info/LICENSE
lib_ml_remla10_2024-1.0.2.dist-info/METADATA
lib_ml_remla10_2024-1.0.2.dist-info/WHEEL
lib_ml_remla10_2024-1.0.2.dist-info/RECORD
