Metadata-Version: 2.1
Name: lib-ml-REMLA10-2024
Version: 1.0.2
Summary: Pre-processing logic for some ML work.
License: MIT
Author: Jan
Author-email: j2000.vdm@gmail.com
Requires-Python: >=3.11,<3.12
Classifier: License :: OSI Approved :: MIT License
Classifier: Programming Language :: Python :: 3
Classifier: Programming Language :: Python :: 3.11
Requires-Dist: keras (==3.3.3)
Requires-Dist: scikit-learn (==1.2.2)
Requires-Dist: tensorflow (>=2.16.1,<2.17.0)
Requires-Dist: tensorflow-intel (>=2.16.1,<2.17.0) ; sys_platform == "win32"
Requires-Dist: tensorflow-io-gcs-filesystem (>=0.31.0,<0.32.0) ; sys_platform == "linux"
Requires-Dist: tensorflow-io-gcs-filesystem (>=0.31.0,<0.32.0) ; sys_platform == "win32"
Requires-Dist: tensorflow-io-gcs-filesystem (>=0.36.0,<0.37.0) ; sys_platform == "darwin"
